Libgenbot/Crossref.py
Libgenbot/Downloader.py
Libgenbot/HTMLparsers.py
Libgenbot/Libgen.py
Libgenbot/LibgenPaper.py
Libgenbot/NetInfo.py
Libgenbot/Paper.py
Libgenbot/PapersFilters.py
Libgenbot/Scholar.py
Libgenbot/__init__.py
Libgenbot/__main__.py
Libgenbot/proxy.py
Libgenbot-1.1.4.dist-info/LICENSE
Libgenbot-1.1.4.dist-info/METADATA
Libgenbot-1.1.4.dist-info/WHEEL
Libgenbot-1.1.4.dist-info/entry_points.txt
Libgenbot-1.1.4.dist-info/top_level.txt
Libgenbot-1.1.4.dist-info/RECORD
